extended_bots/__init__.py
extended_bots/chardetector.py
extended_bots/regex.py
extended_bots/uncrustify.py
rbextendedbots-0.0.3.dist-info/licenses/LICENSE
rbextendedbots-0.0.3.dist-info/METADATA
rbextendedbots-0.0.3.dist-info/WHEEL
rbextendedbots-0.0.3.dist-info/entry_points.txt
rbextendedbots-0.0.3.dist-info/top_level.txt
rbextendedbots-0.0.3.dist-info/RECORD
