Metadata-Version: 2.4
Name: rbExtendedBots
Version: 0.0.3
Summary: Just another Review Bots
Home-page: https://github.com/misery/ExtendedBots
Author: Andre Klitzing
Author-email: aklitzing@gmail.com
License: MIT
Classifier: Development Status :: 5 - Production/Stable
Classifier: Environment :: Console
Classifier: Framework :: Review Board
Classifier: Intended Audience :: Developers
Classifier: License :: OSI Approved :: MIT License
Classifier: Operating System :: OS Independent
Classifier: Programming Language :: Python
Classifier: Programming Language :: Python :: 2
Classifier: Programming Language :: Python :: 2.7
Classifier: Topic :: Software Development
Classifier: Topic :: Software Development :: Quality Assurance
License-File: LICENSE
Requires-Dist: chardet>=2.3.0
Requires-Dist: reviewbot-worker>=3.0
Requires-Dist: RBTools>=1.0
Dynamic: author
Dynamic: author-email
Dynamic: classifier
Dynamic: description
Dynamic: home-page
Dynamic: license
Dynamic: license-file
Dynamic: requires-dist
Dynamic: summary
